{
    "Use_Defaults": 1,
    "Campaign_Name": "Generic Seattle Regression Campaign",
    "Events": [{
        "Start_Day": 10,
        "class": "CampaignEvent",
        "Nodeset_Config": {
            "class": "NodeSetAll"
        },
        "Event_Coordinator_Config": {
            "class": "StandardInterventionDistributionEventCoordinator",
            "Target_Demographic": "Everyone",
            "Demographic_Coverage": 1.0,
            "Intervention_Config": {
                "class": "IndividualImmunityChanger",
                "Cost_To_Consumer": 10.0,
                "Prime_Acquire": 0.1,
                "Prime_Transmit": 0.2,
                "Prime_Mortality": 0.3,
                "Boost_Acquire": 0.7,
                "Boost_Transmit": 0.7,
                "Boost_Mortality": 1.0,
                "Boost_Threshold_Acquire": 0.2,
                "Boost_Threshold_Transmit": 0.1,
                "Boost_Threshold_Mortality": 0.1
            }
        }
    }]
}